hdl/rtl/gcd_avalon.sv
/*******************************************************************************/
// Design: GCD Calculator Avalon Slave
//  * Wraps NIOS2 GCD Custom Instruction hardware with an Avalon compliant
//    interface. Port names are constructed such that the Quartus
//    Component Designer will auto-infer interface assignments.
//  * Includes done interrupt. Read status to clear.
// Author: Nicholas Strong
/******************************************************************************/
module gcd_avalon (
        input  logic [1:0]  avs_s0_address,    //   avs_s0.address
        input  logic        avs_s0_read,       //         .read
        output logic [31:0] avs_s0_readdata,   //         .readdata
        input  logic        avs_s0_write,      //         .write
        input  logic [31:0] avs_s0_writedata,  //         .writedata
        output logic        ins_irq0_irq,      //  ins_irq.irq0
        input  logic        csi_clk,           //    clock.clk
        input  logic        rsi_reset          //    reset.reset
    );

    /***** Parameters *********************************************************/
    localparam   OP_A = 0;
    localparam   OP_B = 1;
    localparam RESULT = 2;
    localparam STATUS = 3;
    /***** Signals ************************************************************/
    logic [31:0] from_reg [0:3];
    logic [31:0] to_reg [0:3]; // cant do from_reg, to_reg - simulation warnings
    logic [31:0] result, status;
    logic write_en [0:3];
    logic wr_int, done, done_sb, int_clr;
    /**************************************************************************/

    // Register Write Data Assignment //
    assign to_reg[  OP_A] = (avs_s0_address == OP_A) ? avs_s0_writedata : 32'h0;
    assign to_reg[  OP_B] = (avs_s0_address == OP_B) ? avs_s0_writedata : 32'h0;
    assign to_reg[RESULT] = result;
    assign to_reg[STATUS] = {{31{1'b0}},done_sb};

    // Register Write Enable Assignment //
    assign write_en[  OP_A] = (avs_s0_address == OP_A) ? avs_s0_write : 1'b0;
    assign write_en[  OP_B] = (avs_s0_address == OP_B) ? avs_s0_write : 1'b0;
    assign write_en[RESULT] = done;
    assign write_en[STATUS] = 1'b1;

    // 32 Bit Registers //
    // module FF (clk, reset, en, d, q);
    FF #(32) GCD_A (csi_clk, rsi_reset, write_en[  OP_A], to_reg[  OP_A], from_reg[  OP_A]);
    FF #(32) GCD_B (csi_clk, rsi_reset, write_en[  OP_B], to_reg[  OP_B], from_reg[  OP_B]);
    FF #(32) GCD_C (csi_clk, rsi_reset, write_en[RESULT], to_reg[RESULT], from_reg[RESULT]);
    FF #(32) GCD_S (csi_clk, rsi_reset, write_en[STATUS], to_reg[STATUS], from_reg[STATUS]);

    assign avs_s0_readdata = avs_s0_read ? from_reg[avs_s0_address] : 32'h0;

    // Set Reset FF //
    // Creates a sticky bit for holding status. Set on done.
    // Cleared on write to OP_B.
    //
    // module set_reset(clk, clk_en, reset, en, clr, out);
    set_reset SR (csi_clk, 1'b1, rsi_reset, done, write_en[OP_B], done_sb);

    // Flip Flops //
    // Delays the write enable to OP_B by one cycle, allowing
    // time for the OP_B to show up at the output.
    //
    // module FF (clk, reset, en, d, q);
    FF FF0 (csi_clk, rsi_reset, 1'b1, write_en[OP_B], wr_int);

    // GCD Custom Instruction //
    // module gcd_ci(clk, reset, clk_en, start, dataa, datab, done, result);
    gcd_ci GCD (
        .clk   (csi_clk),
        .reset (rsi_reset),
        .clk_en(1'b1),
        .start (wr_int),
        .dataa (from_reg[OP_A]),
        .datab (from_reg[OP_B]),
        .done  (done),
        .result(result));

    // Done Interrupt //
    // Creates a sticky bit for the irq interrupt. Set on done.
    // Cleared by a read to the status register.
    //
    // module set_reset(clk, clk_en, reset, en, clr, out);
    set_reset D_INT (csi_clk, 1'b1, rsi_reset, done, int_clr, ins_irq0_irq);
    assign int_clr = (avs_s0_read & ((avs_s0_address == STATUS))) ? 1'b1 : 1'b0;

endmodule
/**endmodule********************************************************************/


/*******************************************************************************/
// GCD Custom Instruction
// * Implements Euclid's algorithm via subtraction
/*******************************************************************************/
module gcd_ci(clk, reset, clk_en, start, dataa, datab, done, result);
    input logic clk;
    input logic reset;
    input logic clk_en;
    input logic start;
    input logic [31:0] dataa;
    input logic [31:0] datab;
    output logic done;
    output logic [31:0] result;

    logic unsigned [31:0] a;
    logic unsigned [31:0] b;

    // Done internal and edge detect is just done because
    // the custom instruction protocol wants a pulse.
    logic done_internal;
    edge_detect ED (clk, clk_en, reset, done_internal, done);

    always @(posedge clk)
    begin
        if (reset) begin
        done_internal <=  1'b1;
        a             <= 32'hDEADDEAD;
        b             <= 32'hDEADDEAD;
        result        <= 32'hDEADDEAD;
        end
        else begin
            if(clk_en) begin
                if (start) begin
                    done_internal <= 1'b0;
                    a             <= dataa;
                    b             <= datab;
                end
                else if (!done_internal) begin
                    if (b == 32'h0) begin
                        done_internal <= 1'b1;
                        result        <= a;
                    end
                    else if (a > b) begin
                        a <= a - b;
                    end
                    else begin
                        b <= b - a;
                    end
                end
            end
        end
    end
endmodule
/**endmodule********************************************************************/


/*******************************************************************************/
// Edge Detect
// * Supports rising and falling edges
// * May produce incorrect edges off reset.
// * TODO: Add parameterized initial value.
// * TODO: Add logic to prevent reset edges (hint: xor)
/*******************************************************************************/
module edge_detect #(parameter RISING=1)(clk, clk_en, reset, in, e);
    input  logic clk;
    input  logic clk_en;
    input  logic reset;
    input  logic in;
    output logic e;

    reg tmp;

    always @(posedge clk)
    begin
        if (reset) // Synchronous reset when reset goes high
            tmp <= in;
        else begin
            if (clk_en)
                tmp <= in;
        end
    end

    assign e = RISING ? (~tmp & in) : (tmp & ~in);
endmodule
/**endmodule********************************************************************/


/*******************************************************************************/
// Set Reset FF
// * Also called a sticky bit
// * Intended to be used for custom instruction, thus the clk_en. Was not.
/*******************************************************************************/
module set_reset(clk, clk_en, reset, en, clr, out);
    input  logic clk;
    input  logic clk_en;
    input  logic reset;
    input  logic en;
  	input  logic clr;
    output logic out;

    always @(posedge clk)
    begin
        if (reset) // Synchronous reset when reset goes high
            out <= 1'b0;
        else begin
            if (clk_en & en)
                out <= 1'b1;
            else if (clk_en & clr)
                out <= 1'b0;
        end
    end
endmodule
/**endmodule********************************************************************/


/*******************************************************************************/
 // Flip Flop
 // * Width customizable flip flop with en
 // * TODO: Add parameterized initial value.
 /*******************************************************************************/
module FF (clk, reset, en, d, q);
    parameter WIDTH = 1;
    input  logic clk;
    input  logic reset;
    input  logic en;
    input  logic [WIDTH-1:0] d;
    output logic [WIDTH-1:0] q;


    always @(posedge clk)
    begin
        if (reset)
            q <= 0;
        else if (en)
            q <= d;
        else
            q <= q;
    end
endmodule
/**endmodule********************************************************************/

hdl/behav/tb.sv
// Testbench
module tb;

  logic clk, rst, rd, wr, cs, doneInt;
  logic [1:0] addr;
  logic [3:0] be;
  logic [31:0] wrData, rdData;

  // Instantiate design under test
  gcd_avalon DUT (
    .avs_s0_address(addr),
    .avs_s0_read(rd),
    .avs_s0_readdata(rdData),
    .avs_s0_write(wr),
    .avs_s0_writedata(wrData),
    .ins_irq0_irq(doneInt),
    .csi_clk(clk),
    .rsi_reset(rst)
  );

  integer test_vec[][2] = '{
    '{91, 21},
    '{1,1},
    '{2,1023}
    //'{2147483647,524287},
    //'{1000000000,1},
  };

  initial begin
    clk = 0;
    #5
  	forever #5 clk = ~clk;
  end

  initial begin
    $display("Reset flop.");
  	rst = 1;

    repeat (2) @(posedge clk);
    $display("Release reset.");
    rst = 0;
  end

  initial begin
    // Dump waves
    $dumpfile("dump.vcd");
    $dumpvars();

    // Initialize
    cs = 1;
    be = 4'hF;
    wrData = 0;
    addr = 0;
    wr = 0;
    rd = 0;

    // Take out of reset
    @(negedge rst);
    repeat (3) @(posedge clk);

    // Test
    foreach(test_vec[i])
    begin
      $display("i:%0h", i);
      addr = 0;
      wrData = test_vec[i][0];
      wr = 1;
      @(posedge clk);
      addr = 1;
      wrData = test_vec[i][1];
      @(posedge clk);
      addr = 3;
      wr = 0;
      rd = 1;
      @(posedge rdData[0]);
      repeat (2)@(posedge clk);
      rd = 0;
      @(posedge clk);
      rd = 1;
      addr = 2;
      @(posedge clk);
    end

    repeat (3) @(posedge clk);
    $finish;
  end

endmodule

simulation/modelsim/dump.vcd
$date
	Wed Nov 17 19:25:00 2021
$end
$version
	ModelSim Version 10.5b
$end
$timescale
	1ps
$end

$scope module tb $end
$var reg 1 ! clk $end
$var reg 1 " rst $end
$var reg 1 # rd $end
$var reg 1 $ wr $end
$var reg 1 % cs $end
$var reg 1 & doneInt $end
$var reg 2 ' addr [1:0] $end
$var reg 4 ( be [3:0] $end
$var reg 32 ) wrData [31:0] $end
$var reg 32 * rdData [31:0] $end

$scope module DUT $end
$var parameter 32 + OP_A $end
$var parameter 32 , OP_B $end
$var parameter 32 - RESULT $end
$var parameter 32 . STATUS $end
$var wire 1 / avs_s0_address [1] $end
$var wire 1 0 avs_s0_address [0] $end
$var wire 1 1 avs_s0_read $end
$var reg 32 2 avs_s0_readdata [31:0] $end
$var wire 1 3 avs_s0_write $end
$var wire 1 4 avs_s0_writedata [31] $end
$var wire 1 5 avs_s0_writedata [30] $end
$var wire 1 6 avs_s0_writedata [29] $end
$var wire 1 7 avs_s0_writedata [28] $end
$var wire 1 8 avs_s0_writedata [27] $end
$var wire 1 9 avs_s0_writedata [26] $end
$var wire 1 : avs_s0_writedata [25] $end
$var wire 1 ; avs_s0_writedata [24] $end
$var wire 1 < avs_s0_writedata [23] $end
$var wire 1 = avs_s0_writedata [22] $end
$var wire 1 > avs_s0_writedata [21] $end
$var wire 1 ? avs_s0_writedata [20] $end
$var wire 1 @ avs_s0_writedata [19] $end
$var wire 1 A avs_s0_writedata [18] $end
$var wire 1 B avs_s0_writedata [17] $end
$var wire 1 C avs_s0_writedata [16] $end
$var wire 1 D avs_s0_writedata [15] $end
$var wire 1 E avs_s0_writedata [14] $end
$var wire 1 F avs_s0_writedata [13] $end
$var wire 1 G avs_s0_writedata [12] $end
$var wire 1 H avs_s0_writedata [11] $end
$var wire 1 I avs_s0_writedata [10] $end
$var wire 1 J avs_s0_writedata [9] $end
$var wire 1 K avs_s0_writedata [8] $end
$var wire 1 L avs_s0_writedata [7] $end
$var wire 1 M avs_s0_writedata [6] $end
$var wire 1 N avs_s0_writedata [5] $end
$var wire 1 O avs_s0_writedata [4] $end
$var wire 1 P avs_s0_writedata [3] $end
$var wire 1 Q avs_s0_writedata [2] $end
$var wire 1 R avs_s0_writedata [1] $end
$var wire 1 S avs_s0_writedata [0] $end
$var reg 1 T ins_irq0_irq $end
$var wire 1 U csi_clk $end
$var wire 1 V rsi_reset $end
$var reg 32 W result [31:0] $end
$var reg 32 X status [31:0] $end
$var reg 1 Y wr_int $end
$var reg 1 Z done $end
$var reg 1 [ done_sb $end
$var reg 1 \ int_clr $end

$scope module GCD_A $end
$var parameter 32 ] WIDTH $end
$var reg 1 ^ clk $end
$var reg 1 _ reset $end
$var reg 1 ` en $end
$var reg 32 a d [31:0] $end
$var reg 32 b q [31:0] $end
$upscope $end

$scope module GCD_B $end
$var parameter 32 c WIDTH $end
$var reg 1 d clk $end
$var reg 1 e reset $end
$var reg 1 f en $end
$var reg 32 g d [31:0] $end
$var reg 32 h q [31:0] $end
$upscope $end

$scope module GCD_C $end
$var parameter 32 i WIDTH $end
$var reg 1 j clk $end
$var reg 1 k reset $end
$var reg 1 l en $end
$var reg 32 m d [31:0] $end
$var reg 32 n q [31:0] $end
$upscope $end

$scope module GCD_S $end
$var parameter 32 o WIDTH $end
$var reg 1 p clk $end
$var reg 1 q reset $end
$var reg 1 r en $end
$var reg 32 s d [31:0] $end
$var reg 32 t q [31:0] $end
$upscope $end

$scope module SR $end
$var reg 1 u clk $end
$var reg 1 v clk_en $end
$var reg 1 w reset $end
$var reg 1 x en $end
$var reg 1 y clr $end
$var reg 1 z out $end
$upscope $end

$scope module FF0 $end
$var parameter 32 { WIDTH $end
$var reg 1 | clk $end
$var reg 1 } reset $end
$var reg 1 ~ en $end
$var reg 1 !! d [0:0] $end
$var reg 1 "! q [0:0] $end
$upscope $end

$scope module GCD $end
$var reg 1 #! clk $end
$var reg 1 $! reset $end
$var reg 1 %! clk_en $end
$var reg 1 &! start $end
$var reg 32 '! dataa [31:0] $end
$var reg 32 (! datab [31:0] $end
$var reg 1 )! done $end
$var reg 32 *! result [31:0] $end
$var reg 32 +! a [31:0] $end
$var reg 32 ,! b [31:0] $end
$var reg 1 -! done_internal $end

$scope module ED $end
$var parameter 32 .! RISING $end
$var reg 1 /! clk $end
$var reg 1 0! clk_en $end
$var reg 1 1! reset $end
$var reg 1 2! in $end
$var reg 1 3! e $end
$var reg 1 4! tmp $end
$upscope $end
$upscope $end

$scope module D_INT $end
$var reg 1 5! clk $end
$var reg 1 6! clk_en $end
$var reg 1 7! reset $end
$var reg 1 8! en $end
$var reg 1 9! clr $end
$var reg 1 :! out $end
$upscope $end
$upscope $end
$upscope $end

$scope begin std $end
$upscope $end
$enddefinitions $end
#0
$dumpvars
0!
1"
0#
0$
1%
x&
b0 '
b1111 (
b0 )
b0 *
b0 2
xT
bx W
bx X
xY
xZ
x[
0\
0^
1_
0`
b0 a
bx b
0d
1e
0f
b0 g
bx h
0j
1k
xl
bx m
bx n
0p
1q
1r
b0x s
bx t
0u
1v
1w
xx
0y
xz
0|
1}
1~
b0 !!
bx "!
0#!
1$!
1%!
x&!
bx '!
bx (!
x)!
bx *!
bx +!
bx ,!
x-!
0/!
10!
11!
x2!
x3!
x4!
05!
16!
17!
x8!
09!
x:!
b0 +
b1 ,
b10 -
b11 .
b100000 ]
b100000 c
b100000 i
b100000 o
b1 {
b1 .!
00
0/
01
03
0S
0R
0Q
0P
0O
0N
0M
0L
0K
0J
0I
0H
0G
0F
0E
0D
0C
0B
0A
0@
0?
0>
0=
0<
0;
0:
09
08
07
06
05
04
0U
1V
$end
#10
1!
1U
1^
1d
1j
1p
1u
1|
1#!
15!
1/!
0:!
1-!
b11011110101011011101111010101101 +!
b11011110101011011101111010101101 ,!
b11011110101011011101111010101101 *!
b0 "!
0z
b0 t
b0 n
b0 h
b0 b
0[
0Y
b11011110101011011101111010101101 W
12!
0T
0&
0&!
b0 '!
b0 (!
b11011110101011011101111010101101 m
b0 s
#15
0!
0U
0^
0d
0j
0p
0u
0|
0#!
05!
0/!
#20
1!
1U
1^
1d
1j
1p
1u
1|
1#!
15!
1/!
0"
0V
0_
0e
0k
0q
0w
0}
0$!
07!
01!
14!
03!
0)!
0Z
0x
08!
0l
#25
0!
0U
0^
0d
0j
0p
0u
0|
0#!
05!
0/!
#30
1!
1U
1^
1d
1j
1p
1u
1|
1#!
15!
1/!
#35
0!
0U
0^
0d
0j
0p
0u
0|
0#!
05!
0/!
#40
1!
1U
1^
1d
1j
1p
1u
1|
1#!
15!
1/!
#45
0!
0U
0^
0d
0j
0p
0u
0|
0#!
05!
0/!
#50
1!
1U
1^
1d
1j
1p
1u
1|
1#!
15!
1/!
b1011011 )
1$
1S
1R
1P
1O
1M
13
b1011011 a
1`
#55
0!
0U
0^
0d
0j
0p
0u
0|
0#!
05!
0/!
#60
1!
1U
1^
1d
1j
1p
1u
1|
1#!
15!
1/!
b1 '
b10101 )
0R
1Q
0P
0M
10
b0 a
b10101 g
0`
1f
1y
b1 !!
b1011011 b
b1011011 '!
#65
0!
0U
0^
0d
0j
0p
0u
0|
0#!
05!
0/!
#70
1!
1U
1^
1d
1j
1p
1u
1|
1#!
15!
1/!
b11 '
0$
1#
1/
03
11
1\
19!
0f
0y
b0 !!
b0 g
b1 "!
b10101 h
1Y
1&!
b10101 (!
#75
0!
0U
0^
0d
0j
0p
0u
0|
0#!
05!
0/!
#80
1!
1U
1^
1d
1j
1p
1u
1|
1#!
15!
1/!
0-!
b1011011 +!
b10101 ,!
b0 "!
0Y
02!
0&!
#85
0!
0U
0^
0d
0j
0p
0u
0|
0#!
05!
0/!
#90
1!
1U
1^
1d
1j
1p
1u
1|
1#!
15!
1/!
04!
b1000110 +!
#95
0!
0U
0^
0d
0j
0p
0u
0|
0#!
05!
0/!
#100
1!
1U
1^
1d
1j
1p
1u
1|
1#!
15!
1/!
b110001 +!
#105
0!
0U
0^
0d
0j
0p
0u
0|
0#!
05!
0/!
#110
1!
1U
1^
1d
1j
1p
1u
1|
1#!
15!
1/!
b11100 +!
#115
0!
0U
0^
0d
0j
0p
0u
0|
0#!
05!
0/!
#120
1!
1U
1^
1d
1j
1p
1u
1|
1#!
15!
1/!
b111 +!
#125
0!
0U
0^
0d
0j
0p
0u
0|
0#!
05!
0/!
#130
1!
1U
1^
1d
1j
1p
1u
1|
1#!
15!
1/!
b1110 ,!
#135
0!
0U
0^
0d
0j
0p
0u
0|
0#!
05!
0/!
#140
1!
1U
1^
1d
1j
1p
1u
1|
1#!
15!
1/!
b111 ,!
#145
0!
0U
0^
0d
0j
0p
0u
0|
0#!
05!
0/!
#150
1!
1U
1^
1d
1j
1p
1u
1|
1#!
15!
1/!
b0 ,!
#155
0!
0U
0^
0d
0j
0p
0u
0|
0#!
05!
0/!
#160
1!
1U
1^
1d
1j
1p
1u
1|
1#!
15!
1/!
1-!
b111 *!
b111 W
12!
13!
b111 m
1)!
1Z
1x
18!
1l
#165
0!
0U
0^
0d
0j
0p
0u
0|
0#!
05!
0/!
#170
1!
1U
1^
1d
1j
1p
1u
1|
1#!
15!
1/!
14!
1:!
1z
b111 n
1[
1T
03!
0)!
1&
b1 s
0Z
0x
08!
0l
#175
0!
0U
0^
0d
0j
0p
0u
0|
0#!
05!
0/!
#180
1!
1U
1^
1d
1j
1p
1u
1|
1#!
15!
1/!
0:!
b1 t
0T
0&
b1 2
b1 *
#185
0!
0U
0^
0d
0j
0p
0u
0|
0#!
05!
0/!
#190
1!
1U
1^
1d
1j
1p
1u
1|
1#!
15!
1/!
#195
0!
0U
0^
0d
0j
0p
0u
0|
0#!
05!
0/!
#200
1!
1U
1^
1d
1j
1p
1u
1|
1#!
15!
1/!
0#
01
b0 2
0\
09!
b0 *
#205
0!
0U
0^
0d
0j
0p
0u
0|
0#!
05!
0/!
#210
1!
1U
1^
1d
1j
1p
1u
1|
1#!
15!
1/!
1#
b10 '
11
00
b111 2
b111 *
#215
0!
0U
0^
0d
0j
0p
0u
0|
0#!
05!
0/!
#220
1!
1U
1^
1d
1j
1p
1u
1|
1#!
15!
1/!
b0 '
b1 )
1$
0Q
0O
0/
13
b1011011 2
b1 a
b1011011 *
1`
#225
0!
0U
0^
0d
0j
0p
0u
0|
0#!
05!
0/!
#230
1!
1U
1^
1d
1j
1p
1u
1|
1#!
15!
1/!
b1 '
10
b10101 2
b10101 *
0`
1f
1y
b1 !!
b0 a
b1 g
b1 b
b1 '!
#235
0!
0U
0^
0d
0j
0p
0u
0|
0#!
05!
0/!
#240
1!
1U
1^
1d
1j
1p
1u
1|
1#!
15!
1/!
b11 '
0$
1/
03
b1 2
1\
19!
b1 *
0f
0y
b0 !!
b0 g
b1 "!
0z
b1 h
0[
1Y
1&!
b1 (!
b0 s
#245
0!
0U
0^
0d
0j
0p
0u
0|
0#!
05!
0/!
#250
1!
1U
1^
1d
1j
1p
1u
1|
1#!
15!
1/!
0-!
b1 +!
b1 ,!
b0 "!
b0 t
0Y
02!
0&!
b0 2
b0 *
#255
0!
0U
0^
0d
0j
0p
0u
0|
0#!
05!
0/!
#260
1!
1U
1^
1d
1j
1p
1u
1|
1#!
15!
1/!
04!
b0 ,!
#265
0!
0U
0^
0d
0j
0p
0u
0|
0#!
05!
0/!
#270
1!
1U
1^
1d
1j
1p
1u
1|
1#!
15!
1/!
1-!
b1 *!
b1 W
12!
13!
b1 m
1)!
1Z
1x
18!
1l
#275
0!
0U
0^
0d
0j
0p
0u
0|
0#!
05!
0/!
#280
1!
1U
1^
1d
1j
1p
1u
1|
1#!
15!
1/!
14!
1:!
1z
b1 n
1[
1T
03!
0)!
1&
b1 s
0Z
0x
08!
0l
#285
0!
0U
0^
0d
0j
0p
0u
0|
0#!
05!
0/!
#290
1!
1U
1^
1d
1j
1p
1u
1|
1#!
15!
1/!
0:!
b1 t
0T
0&
b1 2
b1 *
#295
0!
0U
0^
0d
0j
0p
0u
0|
0#!
05!
0/!
#300
1!
1U
1^
1d
1j
1p
1u
1|
1#!
15!
1/!
#305
0!
0U
0^
0d
0j
0p
0u
0|
0#!
05!
0/!
#310
1!
1U
1^
1d
1j
1p
1u
1|
1#!
15!
1/!
0#
01
b0 2
0\
09!
b0 *
#315
0!
0U
0^
0d
0j
0p
0u
0|
0#!
05!
0/!
#320
1!
1U
1^
1d
1j
1p
1u
1|
1#!
15!
1/!
1#
b10 '
11
00
b1 2
b1 *
#325
0!
0U
0^
0d
0j
0p
0u
0|
0#!
05!
0/!
#330
1!
1U
1^
1d
1j
1p
1u
1|
1#!
15!
1/!
b0 '
b10 )
1$
0S
1R
0/
13
b10 a
1`
#335
0!
0U
0^
0d
0j
0p
0u
0|
0#!
05!
0/!
#340
1!
1U
1^
1d
1j
1p
1u
1|
1#!
15!
1/!
b1 '
b1111111111 )
1S
1Q
1P
1O
1N
1M
1L
1K
1J
10
b0 a
b1111111111 g
0`
1f
1y
b1 !!
b10 b
b10 '!
#345
0!
0U
0^
0d
0j
0p
0u
0|
0#!
05!
0/!
#350
1!
1U
1^
1d
1j
1p
1u
1|
1#!
15!
1/!
b11 '
0$
1/
03
1\
19!
0f
0y
b0 !!
b0 g
b1 "!
0z
b1111111111 h
0[
1Y
1&!
b1111111111 (!
b0 s
#355
0!
0U
0^
0d
0j
0p
0u
0|
0#!
05!
0/!
#360
1!
1U
1^
1d
1j
1p
1u
1|
1#!
15!
1/!
0-!
b10 +!
b1111111111 ,!
b0 "!
b0 t
0Y
02!
0&!
b0 2
b0 *
#365
0!
0U
0^
0d
0j
0p
0u
0|
0#!
05!
0/!
#370
1!
1U
1^
1d
1j
1p
1u
1|
1#!
15!
1/!
04!
b1111111101 ,!
#375
0!
0U
0^
0d
0j
0p
0u
0|
0#!
05!
0/!
#380
1!
1U
1^
1d
1j
1p
1u
1|
1#!
15!
1/!
b1111111011 ,!
#385
0!
0U
0^
0d
0j
0p
0u
0|
0#!
05!
0/!
#390
1!
1U
1^
1d
1j
1p
1u
1|
1#!
15!
1/!
b1111111001 ,!
#395
0!
0U
0^
0d
0j
0p
0u
0|
0#!
05!
0/!
#400
1!
1U
1^
1d
1j
1p
1u
1|
1#!
15!
1/!
b1111110111 ,!
#405
0!
0U
0^
0d
0j
0p
0u
0|
0#!
05!
0/!
#410
1!
1U
1^
1d
1j
1p
1u
1|
1#!
15!
1/!
b1111110101 ,!
#415
0!
0U
0^
0d
0j
0p
0u
0|
0#!
05!
0/!
#420
1!
1U
1^
1d
1j
1p
1u
1|
1#!
15!
1/!
b1111110011 ,!
#425
0!
0U
0^
0d
0j
0p
0u
0|
0#!
05!
0/!
#430
1!
1U
1^
1d
1j
1p
1u
1|
1#!
15!
1/!
b1111110001 ,!
#435
0!
0U
0^
0d
0j
0p
0u
0|
0#!
05!
0/!
#440
1!
1U
1^
1d
1j
1p
1u
1|
1#!
15!
1/!
b1111101111 ,!
#445
0!
0U
0^
0d
0j
0p
0u
0|
0#!
05!
0/!
#450
1!
1U
1^
1d
1j
1p
1u
1|
1#!
15!
1/!
b1111101101 ,!
#455
0!
0U
0^
0d
0j
0p
0u
0|
0#!
05!
0/!
#460
1!
1U
1^
1d
1j
1p
1u
1|
1#!
15!
1/!
b1111101011 ,!
#465
0!
0U
0^
0d
0j
0p
0u
0|
0#!
05!
0/!
#470
1!
1U
1^
1d
1j
1p
1u
1|
1#!
15!
1/!
b1111101001 ,!
#475
0!
0U
0^
0d
0j
0p
0u
0|
0#!
05!
0/!
#480
1!
1U
1^
1d
1j
1p
1u
1|
1#!
15!
1/!
b1111100111 ,!
#485
0!
0U
0^
0d
0j
0p
0u
0|
0#!
05!
0/!
#490
1!
1U
1^
1d
1j
1p
1u
1|
1#!
15!
1/!
b1111100101 ,!
#495
0!
0U
0^
0d
0j
0p
0u
0|
0#!
05!
0/!
#500
1!
1U
1^
1d
1j
1p
1u
1|
1#!
15!
1/!
b1111100011 ,!
#505
0!
0U
0^
0d
0j
0p
0u
0|
0#!
05!
0/!
#510
1!
1U
1^
1d
1j
1p
1u
1|
1#!
15!
1/!
b1111100001 ,!
#515
0!
0U
0^
0d
0j
0p
0u
0|
0#!
05!
0/!
#520
1!
1U
1^
1d
1j
1p
1u
1|
1#!
15!
1/!
b1111011111 ,!
#525
0!
0U
0^
0d
0j
0p
0u
0|
0#!
05!
0/!
#530
1!
1U
1^
1d
1j
1p
1u
1|
1#!
15!
1/!
b1111011101 ,!
#535
0!
0U
0^
0d
0j
0p
0u
0|
0#!
05!
0/!
#540
1!
1U
1^
1d
1j
1p
1u
1|
1#!
15!
1/!
b1111011011 ,!
#545
0!
0U
0^
0d
0j
0p
0u
0|
0#!
05!
0/!
#550
1!
1U
1^
1d
1j
1p
1u
1|
1#!
15!
1/!
b1111011001 ,!
#555
0!
0U
0^
0d
0j
0p
0u
0|
0#!
05!
0/!
#560
1!
1U
1^
1d
1j
1p
1u
1|
1#!
15!
1/!
b1111010111 ,!
#565
0!
0U
0^
0d
0j
0p
0u
0|
0#!
05!
0/!
#570
1!
1U
1^
1d
1j
1p
1u
1|
1#!
15!
1/!
b1111010101 ,!
#575
0!
0U
0^
0d
0j
0p
0u
0|
0#!
05!
0/!
#580
1!
1U
1^
1d
1j
1p
1u
1|
1#!
15!
1/!
b1111010011 ,!
#585
0!
0U
0^
0d
0j
0p
0u
0|
0#!
05!
0/!
#590
1!
1U
1^
1d
1j
1p
1u
1|
1#!
15!
1/!
b1111010001 ,!
#595
0!
0U
0^
0d
0j
0p
0u
0|
0#!
05!
0/!
#600
1!
1U
1^
1d
1j
1p
1u
1|
1#!
15!
1/!
b1111001111 ,!
#605
0!
0U
0^
0d
0j
0p
0u
0|
0#!
05!
0/!
#610
1!
1U
1^
1d
1j
1p
1u
1|
1#!
15!
1/!
b1111001101 ,!
#615
0!
0U
0^
0d
0j
0p
0u
0|
0#!
05!
0/!
#620
1!
1U
1^
1d
1j
1p
1u
1|
1#!
15!
1/!
b1111001011 ,!
#625
0!
0U
0^
0d
0j
0p
0u
0|
0#!
05!
0/!
#630
1!
1U
1^
1d
1j
1p
1u
1|
1#!
15!
1/!
b1111001001 ,!
#635
0!
0U
0^
0d
0j
0p
0u
0|
0#!
05!
0/!
#640
1!
1U
1^
1d
1j
1p
1u
1|
1#!
15!
1/!
b1111000111 ,!
#645
0!
0U
0^
0d
0j
0p
0u
0|
0#!
05!
0/!
#650
1!
1U
1^
1d
1j
1p
1u
1|
1#!
15!
1/!
b1111000101 ,!
#655
0!
0U
0^
0d
0j
0p
0u
0|
0#!
05!
0/!
#660
1!
1U
1^
1d
1j
1p
1u
1|
1#!
15!
1/!
b1111000011 ,!
#665
0!
0U
0^
0d
0j
0p
0u
0|
0#!
05!
0/!
#670
1!
1U
1^
1d
1j
1p
1u
1|
1#!
15!
1/!
b1111000001 ,!
#675
0!
0U
0^
0d
0j
0p
0u
0|
0#!
05!
0/!
#680
1!
1U
1^
1d
1j
1p
1u
1|
1#!
15!
1/!
b1110111111 ,!
#685
0!
0U
0^
0d
0j
0p
0u
0|
0#!
05!
0/!
#690
1!
1U
1^
1d
1j
1p
1u
1|
1#!
15!
1/!
b1110111101 ,!
#695
0!
0U
0^
0d
0j
0p
0u
0|
0#!
05!
0/!
#700
1!
1U
1^
1d
1j
1p
1u
1|
1#!
15!
1/!
b1110111011 ,!
#705
0!
0U
0^
0d
0j
0p
0u
0|
0#!
05!
0/!
#710
1!
1U
1^
1d
1j
1p
1u
1|
1#!
15!
1/!
b1110111001 ,!
#715
0!
0U
0^
0d
0j
0p
0u
0|
0#!
05!
0/!
#720
1!
1U
1^
1d
1j
1p
1u
1|
1#!
15!
1/!
b1110110111 ,!
#725
0!
0U
0^
0d
0j
0p
0u
0|
0#!
05!
0/!
#730
1!
1U
1^
1d
1j
1p
1u
1|
1#!
15!
1/!
b1110110101 ,!
#735
0!
0U
0^
0d
0j
0p
0u
0|
0#!
05!
0/!
#740
1!
1U
1^
1d
1j
1p
1u
1|
1#!
15!
1/!
b1110110011 ,!
#745
0!
0U
0^
0d
0j
0p
0u
0|
0#!
05!
0/!
#750
1!
1U
1^
1d
1j
1p
1u
1|
1#!
15!
1/!
b1110110001 ,!
#755
0!
0U
0^
0d
0j
0p
0u
0|
0#!
05!
0/!
#760
1!
1U
1^
1d
1j
1p
1u
1|
1#!
15!
1/!
b1110101111 ,!
#765
0!
0U
0^
0d
0j
0p
0u
0|
0#!
05!
0/!
#770
1!
1U
1^
1d
1j
1p
1u
1|
1#!
15!
1/!
b1110101101 ,!
#775
0!
0U
0^
0d
0j
0p
0u
0|
0#!
05!
0/!
#780
1!
1U
1^
1d
1j
1p
1u
1|
1#!
15!
1/!
b1110101011 ,!
#785
0!
0U
0^
0d
0j
0p
0u
0|
0#!
05!
0/!
#790
1!
1U
1^
1d
1j
1p
1u
1|
1#!
15!
1/!
b1110101001 ,!
#795
0!
0U
0^
0d
0j
0p
0u
0|
0#!
05!
0/!
#800
1!
1U
1^
1d
1j
1p
1u
1|
1#!
15!
1/!
b1110100111 ,!
#805
0!
0U
0^
0d
0j
0p
0u
0|
0#!
05!
0/!
#810
1!
1U
1^
1d
1j
1p
1u
1|
1#!
15!
1/!
b1110100101 ,!
#815
0!
0U
0^
0d
0j
0p
0u
0|
0#!
05!
0/!
#820
1!
1U
1^
1d
1j
1p
1u
1|
1#!
15!
1/!
b1110100011 ,!
#825
0!
0U
0^
0d
0j
0p
0u
0|
0#!
05!
0/!
#830
1!
1U
1^
1d
1j
1p
1u
1|
1#!
15!
1/!
b1110100001 ,!
#835
0!
0U
0^
0d
0j
0p
0u
0|
0#!
05!
0/!
#840
1!
1U
1^
1d
1j
1p
1u
1|
1#!
15!
1/!
b1110011111 ,!
#845
0!
0U
0^
0d
0j
0p
0u
0|
0#!
05!
0/!
#850
1!
1U
1^
1d
1j
1p
1u
1|
1#!
15!
1/!
b1110011101 ,!
