hdl/rtl/gcd_avalon.sv
module gcd_avalon (
        input  logic [1:0]  avs_s0_address,    // avs_s0.address
        input  logic        avs_s0_read,       //       .read
        output logic [31:0] avs_s0_readdata,   //       .readdata
        input  logic        avs_s0_write,      //       .write
        input  logic [31:0] avs_s0_writedata,  //       .writedata
        input  logic        csi_clk,           //  clock.clk
        input  logic        rsi_reset          //  reset.reset
    );

    logic [31:0] from_reg [0:3];
    logic [31:0] to_reg [0:3]; // cant stack these - simulation warnings
    logic [31:0] result, status;
    logic local_write [0:3];
    logic wrInt, done, doneSB;

    assign to_reg[0] = (avs_s0_address == 2'h0) ? avs_s0_writedata : 32'h0;
    assign to_reg[1] = (avs_s0_address == 2'h1) ? avs_s0_writedata : 32'h0;
    assign to_reg[2] = result;
    assign to_reg[3] = {{31{1'b0}},doneSB};

    assign local_write[0] = (avs_s0_address == 2'h0) ? avs_s0_write : 1'b0;
    assign local_write[1] = (avs_s0_address == 2'h1) ? avs_s0_write : 1'b0;
    assign local_write[2] = done;
    assign local_write[3] = 1'b1;

    // 32 Bit Registers
    // module FF (clk, reset, en, d, q);
    FF #(32) GCD_A (csi_clk, rsi_reset, local_write[0], to_reg[0], from_reg[0]); // OP_A
    FF #(32) GCD_B (csi_clk, rsi_reset, local_write[1], to_reg[1], from_reg[1]); // OP_B
    FF #(32) GCD_C (csi_clk, rsi_reset, local_write[2], to_reg[2], from_reg[2]); // RESULT
    FF #(32) GCD_S (csi_clk, rsi_reset, local_write[3], to_reg[3], from_reg[3]); // STATUS

    assign avs_s0_readdata = avs_s0_read ? from_reg[avs_s0_address] : 32'h0;

    // Set Reset FF
    // module set_reset(clk, clk_en, reset, en, clr, out);
    set_reset SR (csi_clk, 1'b1, rsi_reset, done, local_write[1], doneSB);

    // Flip Flops
    // module FF (clk, reset, en, d, q);
    FF FF0 (csi_clk, rsi_reset, 1'b1, local_write[1], wrInt);

    // GCD Custom Instruction
    // module gcd_ci(clk, reset, clk_en, start, dataa, datab, done, result);
    gcd_ci GCD (
        .clk   (csi_clk),
        .reset (rsi_reset),
        .clk_en(1'b1),
        .start (wrInt),
        .dataa (from_reg[0]),
        .datab (from_reg[1]),
        .done  (done),
        .result(result));

endmodule

// GCD Custom Instruction
module gcd_ci(clk, reset, clk_en, start, dataa, datab, done, result);
    input logic clk;
    input logic reset;
    input logic clk_en;
    input logic start;
    input logic [31:0] dataa;
    input logic [31:0] datab;
    output logic done;
    output logic [31:0] result;

    logic unsigned [31:0] a;
    logic unsigned [31:0] b;

    // Done internal and edge detect is just done because
    // the custom instruction protocol wants a pulse.
    logic done_internal;
    edge_detect ED (clk, clk_en, reset, done_internal, done);

    always @(posedge clk)
    begin
        if (reset) begin
        done_internal <=  1'b1;
        a             <= 32'hDEADDEAD;
        b             <= 32'hDEADDEAD;
        result        <= 32'hDEADDEAD;
        end
        else begin
            if(clk_en) begin
                if (start) begin
                    done_internal <= 1'b0;
                    a             <= dataa;
                    b             <= datab;
                end
                else if (!done_internal) begin
                    if (b == 32'h0) begin
                        done_internal <= 1'b1;
                        result        <= a;
                    end
                    else if (a > b) begin
                        a <= a - b;
                    end
                    else begin
                        b <= b - a;
                    end
                    //$display("a:%0d, b:%0d result:%0h done:%0h",a, b, result, done);
                end
            end
        end
    end
endmodule

// Edge Detect
module edge_detect #(parameter RISING=1)(clk, clk_en, reset, in, e);
    input  logic clk;
    input  logic clk_en;
    input  logic reset;
    input  logic in;
    output logic e;

    reg tmp;

    always @(posedge clk)
    begin
        if (reset) // Synchronous reset when reset goes high
            tmp <= in;
        else begin
            if (clk_en)
                tmp <= in;
        end
    end

    assign e = RISING ? (~tmp & in) : (tmp & ~in);
endmodule

// Set Clear FF
module set_reset(clk, clk_en, reset, en, clr, out);
    input  clk;
    input  clk_en;
    input  reset;
    input  en;
  	input  clr;
    output reg out;

    always @(posedge clk)
    begin
        if (reset) // Synchronous reset when reset goes high
            out <= 1'b0;
        else begin
            if (clk_en & en)
                out <= 1'b1;
            else if (clk_en & clr)
                out <= 1'b0;
        end
    end
endmodule

 // Flip Flop
module FF (clk, reset, en, d, q);
    parameter WIDTH = 1;
    input  logic clk;
    input  logic reset;
    input  logic en;
    input  logic [WIDTH-1:0] d;
    output logic [WIDTH-1:0] q;


    always @(posedge clk)
    begin
        if (reset)
            q <= 0;
        else if (en)
            q <= d;
        else
            q <= q;
    end
endmodule

hdl/behav/tb.sv
// Testbench
module tb;

  logic clk, rst, rd, wr, cs;
  logic [1:0] addr;
  logic [3:0] be;
  logic [31:0] wrData, rdData;

  // Instantiate design under test
  gcd_avalon DUT (
    .avs_s0_address(addr),
    .avs_s0_read(rd),
    .avs_s0_readdata(rdData),
    .avs_s0_write(wr),
    .avs_s0_writedata(wrData),
    .csi_clk(clk),
    .rsi_reset(rst)
  );

  integer test_vec[][2] = '{
    '{91, 21},
    '{1,1},
    '{2,1023}
    //'{2147483647,524287},
    //'{1000000000,1},
  };

  initial begin
    clk = 0;
    #5
  	forever #5 clk = ~clk;
  end

  initial begin
    $display("Reset flop.");
  	rst = 1;

    repeat (2) @(posedge clk);
    $display("Release reset.");
    rst = 0;
  end

  initial begin
    // Dump waves
    $dumpfile("dump.vcd");
    $dumpvars();

    // Initialize
    cs = 1;
    be = 4'hF;
    wrData = 0;
    addr = 0;
    wr = 0;
    rd = 0;

    // Take out of reset
    @(negedge rst);
    repeat (3) @(posedge clk);

    // Test
    foreach(test_vec[i])
    begin
      $display("i:%0h", i);
      addr = 0;
      wrData = test_vec[i][0];
      wr = 1;
      @(posedge clk);
      addr = 1;
      wrData = test_vec[i][1];
      @(posedge clk);
      addr = 3;
      wr = 0;
      rd = 1;
      @(posedge rdData[0]);
      repeat (2)@(posedge clk);
      rd = 0;
      @(posedge clk);
      rd = 1;
      addr = 2;
      @(posedge clk);
    end

    repeat (3) @(posedge clk);
    $finish;
  end

endmodule

simulation/modelsim/dump.vcd
$date
	Wed Nov 17 01:10:30 2021
$end
$version
	ModelSim Version 10.5b
$end
$timescale
	1ps
$end

$scope module tb $end
$var reg 1 ! clk $end
$var reg 1 " rst $end
$var reg 1 # rd $end
$var reg 1 $ wr $end
$var reg 1 % cs $end
$var reg 2 & addr [1:0] $end
$var reg 4 ' be [3:0] $end
$var reg 32 ( wrData [31:0] $end
$var reg 32 ) rdData [31:0] $end

$scope module DUT $end
$var wire 1 * avs_s0_address [1] $end
$var wire 1 + avs_s0_address [0] $end
$var wire 1 , avs_s0_read $end
$var reg 32 - avs_s0_readdata [31:0] $end
$var wire 1 . avs_s0_write $end
$var wire 1 / avs_s0_writedata [31] $end
$var wire 1 0 avs_s0_writedata [30] $end
$var wire 1 1 avs_s0_writedata [29] $end
$var wire 1 2 avs_s0_writedata [28] $end
$var wire 1 3 avs_s0_writedata [27] $end
$var wire 1 4 avs_s0_writedata [26] $end
$var wire 1 5 avs_s0_writedata [25] $end
$var wire 1 6 avs_s0_writedata [24] $end
$var wire 1 7 avs_s0_writedata [23] $end
$var wire 1 8 avs_s0_writedata [22] $end
$var wire 1 9 avs_s0_writedata [21] $end
$var wire 1 : avs_s0_writedata [20] $end
$var wire 1 ; avs_s0_writedata [19] $end
$var wire 1 < avs_s0_writedata [18] $end
$var wire 1 = avs_s0_writedata [17] $end
$var wire 1 > avs_s0_writedata [16] $end
$var wire 1 ? avs_s0_writedata [15] $end
$var wire 1 @ avs_s0_writedata [14] $end
$var wire 1 A avs_s0_writedata [13] $end
$var wire 1 B avs_s0_writedata [12] $end
$var wire 1 C avs_s0_writedata [11] $end
$var wire 1 D avs_s0_writedata [10] $end
$var wire 1 E avs_s0_writedata [9] $end
$var wire 1 F avs_s0_writedata [8] $end
$var wire 1 G avs_s0_writedata [7] $end
$var wire 1 H avs_s0_writedata [6] $end
$var wire 1 I avs_s0_writedata [5] $end
$var wire 1 J avs_s0_writedata [4] $end
$var wire 1 K avs_s0_writedata [3] $end
$var wire 1 L avs_s0_writedata [2] $end
$var wire 1 M avs_s0_writedata [1] $end
$var wire 1 N avs_s0_writedata [0] $end
$var wire 1 O csi_clk $end
$var wire 1 P rsi_reset $end
$var reg 32 Q result [31:0] $end
$var reg 32 R status [31:0] $end
$var reg 1 S wrInt $end
$var reg 1 T done $end
$var reg 1 U doneSB $end

$scope module GCD_A $end
$var parameter 32 V WIDTH $end
$var reg 1 W clk $end
$var reg 1 X reset $end
$var reg 1 Y en $end
$var reg 32 Z d [31:0] $end
$var reg 32 [ q [31:0] $end
$upscope $end

$scope module GCD_B $end
$var parameter 32 \ WIDTH $end
$var reg 1 ] clk $end
$var reg 1 ^ reset $end
$var reg 1 _ en $end
$var reg 32 ` d [31:0] $end
$var reg 32 a q [31:0] $end
$upscope $end

$scope module GCD_C $end
$var parameter 32 b WIDTH $end
$var reg 1 c clk $end
$var reg 1 d reset $end
$var reg 1 e en $end
$var reg 32 f d [31:0] $end
$var reg 32 g q [31:0] $end
$upscope $end

$scope module GCD_S $end
$var parameter 32 h WIDTH $end
$var reg 1 i clk $end
$var reg 1 j reset $end
$var reg 1 k en $end
$var reg 32 l d [31:0] $end
$var reg 32 m q [31:0] $end
$upscope $end

$scope module SR $end
$var wire 1 O clk $end
$var wire 1 n clk_en $end
$var wire 1 P reset $end
$var wire 1 o en $end
$var wire 1 p clr $end
$var reg 1 q out $end
$upscope $end

$scope module FF0 $end
$var parameter 32 r WIDTH $end
$var reg 1 s clk $end
$var reg 1 t reset $end
$var reg 1 u en $end
$var reg 1 v d [0:0] $end
$var reg 1 w q [0:0] $end
$upscope $end

$scope module GCD $end
$var reg 1 x clk $end
$var reg 1 y reset $end
$var reg 1 z clk_en $end
$var reg 1 { start $end
$var reg 32 | dataa [31:0] $end
$var reg 32 } datab [31:0] $end
$var reg 1 ~ done $end
$var reg 32 !! result [31:0] $end
$var reg 32 "! a [31:0] $end
$var reg 32 #! b [31:0] $end
$var reg 1 $! done_internal $end

$scope module ED $end
$var parameter 32 %! RISING $end
$var reg 1 &! clk $end
$var reg 1 '! clk_en $end
$var reg 1 (! reset $end
$var reg 1 )! in $end
$var reg 1 *! e $end
$var reg 1 +! tmp $end
$upscope $end
$upscope $end
$upscope $end
$upscope $end

$scope begin std $end
$upscope $end
$enddefinitions $end
#0
$dumpvars
0!
1"
0#
0$
1%
b0 &
b1111 '
b0 (
b0 )
b0 -
bx Q
bx R
xS
xT
xU
0W
1X
0Y
b0 Z
bx [
0]
1^
0_
b0 `
bx a
0c
1d
xe
bx f
bx g
0i
1j
1k
b0x l
bx m
xq
0s
1t
1u
b0 v
bx w
0x
1y
1z
x{
bx |
bx }
x~
bx !!
bx "!
bx #!
x$!
0&!
1'!
1(!
x)!
x*!
x+!
b100000 V
b100000 \
b100000 b
b100000 h
b1 r
b1 %!
0+
0*
0,
0.
0N
0M
0L
0K
0J
0I
0H
0G
0F
0E
0D
0C
0B
0A
0@
0?
0>
0=
0<
0;
0:
09
08
07
06
05
04
03
02
01
00
0/
0O
1P
1n
xo
0p
$end
#10
1!
1O
1W
1]
1c
1i
1s
1x
1&!
1$!
b11011110101011011101111010101101 "!
b11011110101011011101111010101101 #!
b11011110101011011101111010101101 !!
b0 w
b0 m
b0 g
b0 a
b0 [
0q
0U
0S
b11011110101011011101111010101101 Q
1)!
0{
b0 |
b0 }
b11011110101011011101111010101101 f
b0 l
#15
0!
0O
0W
0]
0c
0i
0s
0x
0&!
#20
1!
1O
1W
1]
1c
1i
1s
1x
1&!
0"
0P
0X
0^
0d
0j
0t
0y
0(!
1+!
0*!
0~
0T
0o
0e
#25
0!
0O
0W
0]
0c
0i
0s
0x
0&!
#30
1!
1O
1W
1]
1c
1i
1s
1x
1&!
#35
0!
0O
0W
0]
0c
0i
0s
0x
0&!
#40
1!
1O
1W
1]
1c
1i
1s
1x
1&!
#45
0!
0O
0W
0]
0c
0i
0s
0x
0&!
#50
1!
1O
1W
1]
1c
1i
1s
1x
1&!
b1011011 (
1$
1N
1M
1K
1J
1H
1.
b1011011 Z
1Y
#55
0!
0O
0W
0]
0c
0i
0s
0x
0&!
#60
1!
1O
1W
1]
1c
1i
1s
1x
1&!
b1 &
b10101 (
0M
1L
0K
0H
1+
b0 Z
b10101 `
0Y
1_
b1 v
1p
b1011011 [
b1011011 |
#65
0!
0O
0W
0]
0c
0i
0s
0x
0&!
#70
1!
1O
1W
1]
1c
1i
1s
1x
1&!
b11 &
0$
1#
1*
0.
1,
0_
b0 v
b0 `
0p
b1 w
b10101 a
1S
1{
b10101 }
#75
0!
0O
0W
0]
0c
0i
0s
0x
0&!
#80
1!
1O
1W
1]
1c
1i
1s
1x
1&!
0$!
b1011011 "!
b10101 #!
b0 w
0S
0)!
0{
#85
0!
0O
0W
0]
0c
0i
0s
0x
0&!
#90
1!
1O
1W
1]
1c
1i
1s
1x
1&!
0+!
b1000110 "!
#95
0!
0O
0W
0]
0c
0i
0s
0x
0&!
#100
1!
1O
1W
1]
1c
1i
1s
1x
1&!
b110001 "!
#105
0!
0O
0W
0]
0c
0i
0s
0x
0&!
#110
1!
1O
1W
1]
1c
1i
1s
1x
1&!
b11100 "!
#115
0!
0O
0W
0]
0c
0i
0s
0x
0&!
#120
1!
1O
1W
1]
1c
1i
1s
1x
1&!
b111 "!
#125
0!
0O
0W
0]
0c
0i
0s
0x
0&!
#130
1!
1O
1W
1]
1c
1i
1s
1x
1&!
b1110 #!
#135
0!
0O
0W
0]
0c
0i
0s
0x
0&!
#140
1!
1O
1W
1]
1c
1i
1s
1x
1&!
b111 #!
#145
0!
0O
0W
0]
0c
0i
0s
0x
0&!
#150
1!
1O
1W
1]
1c
1i
1s
1x
1&!
b0 #!
#155
0!
0O
0W
0]
0c
0i
0s
0x
0&!
#160
1!
1O
1W
1]
1c
1i
1s
1x
1&!
1$!
b111 !!
b111 Q
1)!
1*!
b111 f
1~
1T
1o
1e
#165
0!
0O
0W
0]
0c
0i
0s
0x
0&!
#170
1!
1O
1W
1]
1c
1i
1s
1x
1&!
1+!
b111 g
1q
1U
0*!
0~
b1 l
0T
0o
0e
#175
0!
0O
0W
0]
0c
0i
0s
0x
0&!
#180
1!
1O
1W
1]
1c
1i
1s
1x
1&!
b1 m
b1 -
b1 )
#185
0!
0O
0W
0]
0c
0i
0s
0x
0&!
#190
1!
1O
1W
1]
1c
1i
1s
1x
1&!
#195
0!
0O
0W
0]
0c
0i
0s
0x
0&!
#200
1!
1O
1W
1]
1c
1i
1s
1x
1&!
0#
0,
b0 -
b0 )
#205
0!
0O
0W
0]
0c
0i
0s
0x
0&!
#210
1!
1O
1W
1]
1c
1i
1s
1x
1&!
1#
b10 &
1,
0+
b111 -
b111 )
#215
0!
0O
0W
0]
0c
0i
0s
0x
0&!
#220
1!
1O
1W
1]
1c
1i
1s
1x
1&!
b0 &
b1 (
1$
0L
0J
0*
1.
b1011011 -
b1 Z
b1011011 )
1Y
#225
0!
0O
0W
0]
0c
0i
0s
0x
0&!
#230
1!
1O
1W
1]
1c
1i
1s
1x
1&!
b1 &
1+
b10101 -
b10101 )
0Y
1_
b1 v
b0 Z
b1 `
1p
b1 [
b1 |
#235
0!
0O
0W
0]
0c
0i
0s
0x
0&!
#240
1!
1O
1W
1]
1c
1i
1s
1x
1&!
b11 &
0$
1*
0.
b1 -
b1 )
0_
b0 v
b0 `
0p
b1 w
b1 a
0q
0U
1S
1{
b1 }
b0 l
#245
0!
0O
0W
0]
0c
0i
0s
0x
0&!
#250
1!
1O
1W
1]
1c
1i
1s
1x
1&!
0$!
b1 "!
b1 #!
b0 w
b0 m
0S
0)!
0{
b0 -
b0 )
#255
0!
0O
0W
0]
0c
0i
0s
0x
0&!
#260
1!
1O
1W
1]
1c
1i
1s
1x
1&!
0+!
b0 #!
#265
0!
0O
0W
0]
0c
0i
0s
0x
0&!
#270
1!
1O
1W
1]
1c
1i
1s
1x
1&!
1$!
b1 !!
b1 Q
1)!
1*!
b1 f
1~
1T
1o
1e
#275
0!
0O
0W
0]
0c
0i
0s
0x
0&!
#280
1!
1O
1W
1]
1c
1i
1s
1x
1&!
1+!
b1 g
1q
1U
0*!
0~
b1 l
0T
0o
0e
#285
0!
0O
0W
0]
0c
0i
0s
0x
0&!
#290
1!
1O
1W
1]
1c
1i
1s
1x
1&!
b1 m
b1 -
b1 )
#295
0!
0O
0W
0]
0c
0i
0s
0x
0&!
#300
1!
1O
1W
1]
1c
1i
1s
1x
1&!
#305
0!
0O
0W
0]
0c
0i
0s
0x
0&!
#310
1!
1O
1W
1]
1c
1i
1s
1x
1&!
0#
0,
b0 -
b0 )
#315
0!
0O
0W
0]
0c
0i
0s
0x
0&!
#320
1!
1O
1W
1]
1c
1i
1s
1x
1&!
1#
b10 &
1,
0+
b1 -
b1 )
#325
0!
0O
0W
0]
0c
0i
0s
0x
0&!
#330
1!
1O
1W
1]
1c
1i
1s
1x
1&!
b0 &
b10 (
1$
0N
1M
0*
1.
b10 Z
1Y
#335
0!
0O
0W
0]
0c
0i
0s
0x
0&!
#340
1!
1O
1W
1]
1c
1i
1s
1x
1&!
b1 &
b1111111111 (
1N
1L
1K
1J
1I
1H
1G
1F
1E
1+
b0 Z
b1111111111 `
0Y
1_
b1 v
1p
b10 [
b10 |
#345
0!
0O
0W
0]
0c
0i
0s
0x
0&!
#350
1!
1O
1W
1]
1c
1i
1s
1x
1&!
b11 &
0$
1*
0.
0_
b0 v
b0 `
0p
b1 w
b1111111111 a
0q
0U
1S
1{
b1111111111 }
b0 l
#355
0!
0O
0W
0]
0c
0i
0s
0x
0&!
#360
1!
1O
1W
1]
1c
1i
1s
1x
1&!
0$!
b10 "!
b1111111111 #!
b0 w
b0 m
0S
0)!
0{
b0 -
b0 )
#365
0!
0O
0W
0]
0c
0i
0s
0x
0&!
#370
1!
1O
1W
1]
1c
1i
1s
1x
1&!
0+!
b1111111101 #!
#375
0!
0O
0W
0]
0c
0i
0s
0x
0&!
#380
1!
1O
1W
1]
1c
1i
1s
1x
1&!
b1111111011 #!
#385
0!
0O
0W
0]
0c
0i
0s
0x
0&!
#390
1!
1O
1W
1]
1c
1i
1s
1x
1&!
b1111111001 #!
#395
0!
0O
0W
0]
0c
0i
0s
0x
0&!
#400
1!
1O
1W
1]
1c
1i
1s
1x
1&!
b1111110111 #!
#405
0!
0O
0W
0]
0c
0i
0s
0x
0&!
#410
1!
1O
1W
1]
1c
1i
1s
1x
1&!
b1111110101 #!
#415
0!
0O
0W
0]
0c
0i
0s
0x
0&!
#420
1!
1O
1W
1]
1c
1i
1s
1x
1&!
b1111110011 #!
#425
0!
0O
0W
0]
0c
0i
0s
0x
0&!
#430
1!
1O
1W
1]
1c
1i
1s
1x
1&!
b1111110001 #!
#435
0!
0O
0W
0]
0c
0i
0s
0x
0&!
#440
1!
1O
1W
1]
1c
1i
1s
1x
1&!
b1111101111 #!
#445
0!
0O
0W
0]
0c
0i
0s
0x
0&!
#450
1!
1O
1W
1]
1c
1i
1s
1x
1&!
b1111101101 #!
#455
0!
0O
0W
0]
0c
0i
0s
0x
0&!
#460
1!
1O
1W
1]
1c
1i
1s
1x
1&!
b1111101011 #!
#465
0!
0O
0W
0]
0c
0i
0s
0x
0&!
#470
1!
1O
1W
1]
1c
1i
1s
1x
1&!
b1111101001 #!
#475
0!
0O
0W
0]
0c
0i
0s
0x
0&!
#480
1!
1O
1W
1]
1c
1i
1s
1x
1&!
b1111100111 #!
#485
0!
0O
0W
0]
0c
0i
0s
0x
0&!
#490
1!
1O
1W
1]
1c
1i
1s
1x
1&!
b1111100101 #!
#495
0!
0O
0W
0]
0c
0i
0s
0x
0&!
#500
1!
1O
1W
1]
1c
1i
1s
1x
1&!
b1111100011 #!
#505
0!
0O
0W
0]
0c
0i
0s
0x
0&!
#510
1!
1O
1W
1]
1c
1i
1s
1x
1&!
b1111100001 #!
#515
0!
0O
0W
0]
0c
0i
0s
0x
0&!
#520
1!
1O
1W
1]
1c
1i
1s
1x
1&!
b1111011111 #!
#525
0!
0O
0W
0]
0c
0i
0s
0x
0&!
#530
1!
1O
1W
1]
1c
1i
1s
1x
1&!
b1111011101 #!
#535
0!
0O
0W
0]
0c
0i
0s
0x
0&!
#540
1!
1O
1W
1]
1c
1i
1s
1x
1&!
b1111011011 #!
#545
0!
0O
0W
0]
0c
0i
0s
0x
0&!
#550
1!
1O
1W
1]
1c
1i
1s
1x
1&!
b1111011001 #!
#555
0!
0O
0W
0]
0c
0i
0s
0x
0&!
#560
1!
1O
1W
1]
1c
1i
1s
1x
1&!
b1111010111 #!
#565
0!
0O
0W
0]
0c
0i
0s
0x
0&!
#570
1!
1O
1W
1]
1c
1i
1s
1x
1&!
b1111010101 #!
#575
0!
0O
0W
0]
0c
0i
0s
0x
0&!
#580
1!
1O
1W
1]
1c
1i
1s
1x
1&!
b1111010011 #!
#585
0!
0O
0W
0]
0c
0i
0s
0x
0&!
#590
1!
1O
1W
1]
1c
1i
1s
1x
1&!
b1111010001 #!
#595
0!
0O
0W
0]
0c
0i
0s
0x
0&!
#600
1!
1O
1W
1]
1c
1i
1s
1x
1&!
b1111001111 #!
#605
0!
0O
0W
0]
0c
0i
0s
0x
0&!
#610
1!
1O
1W
1]
1c
1i
1s
1x
1&!
b1111001101 #!
#615
0!
0O
0W
0]
0c
0i
0s
0x
0&!
#620
1!
1O
1W
1]
1c
1i
1s
1x
1&!
b1111001011 #!
#625
0!
0O
0W
0]
0c
0i
0s
0x
0&!
#630
1!
1O
1W
1]
1c
1i
1s
1x
1&!
b1111001001 #!
#635
0!
0O
0W
0]
0c
0i
0s
0x
0&!
#640
1!
1O
1W
1]
1c
1i
1s
1x
1&!
b1111000111 #!
#645
0!
0O
0W
0]
0c
0i
0s
0x
0&!
#650
1!
1O
1W
1]
1c
1i
1s
1x
1&!
b1111000101 #!
#655
0!
0O
0W
0]
0c
0i
0s
0x
0&!
#660
1!
1O
1W
1]
1c
1i
1s
1x
1&!
b1111000011 #!
#665
0!
0O
0W
0]
0c
0i
0s
0x
0&!
#670
1!
1O
1W
1]
1c
1i
1s
1x
1&!
b1111000001 #!
#675
0!
0O
0W
0]
0c
0i
0s
0x
0&!
#680
1!
1O
1W
1]
1c
1i
1s
1x
1&!
b1110111111 #!
#685
0!
0O
0W
0]
0c
0i
0s
0x
0&!
#690
1!
1O
1W
1]
1c
1i
1s
1x
1&!
b1110111101 #!
#695
0!
0O
0W
0]
0c
0i
0s
0x
0&!
#700
1!
1O
1W
1]
1c
1i
1s
1x
1&!
b1110111011 #!
#705
0!
0O
0W
0]
0c
0i
0s
0x
0&!
#710
1!
1O
1W
1]
1c
1i
1s
1x
1&!
b1110111001 #!
#715
0!
0O
0W
0]
0c
0i
0s
0x
0&!
#720
1!
1O
1W
1]
1c
1i
1s
1x
1&!
b1110110111 #!
#725
0!
0O
0W
0]
0c
0i
0s
0x
0&!
#730
1!
1O
1W
1]
1c
1i
1s
1x
1&!
b1110110101 #!
#735
0!
0O
0W
0]
0c
0i
0s
0x
0&!
#740
1!
1O
1W
1]
1c
1i
1s
1x
1&!
b1110110011 #!
#745
0!
0O
0W
0]
0c
0i
0s
0x
0&!
#750
1!
1O
1W
1]
1c
1i
1s
1x
1&!
b1110110001 #!
#755
0!
0O
0W
0]
0c
0i
0s
0x
0&!
#760
1!
1O
1W
1]
1c
1i
1s
1x
1&!
b1110101111 #!
#765
0!
0O
0W
0]
0c
0i
0s
0x
0&!
#770
1!
1O
1W
1]
1c
1i
1s
1x
1&!
b1110101101 #!
#775
0!
0O
0W
0]
0c
0i
0s
0x
0&!
#780
1!
1O
1W
1]
1c
1i
1s
1x
1&!
b1110101011 #!
#785
0!
0O
0W
0]
0c
0i
0s
0x
0&!
#790
1!
1O
1W
1]
1c
1i
1s
1x
1&!
b1110101001 #!
#795
0!
0O
0W
0]
0c
0i
0s
0x
0&!
#800
1!
1O
1W
1]
1c
1i
1s
1x
1&!
b1110100111 #!
#805
0!
0O
0W
0]
0c
0i
0s
0x
0&!
#810
1!
1O
1W
1]
1c
1i
1s
1x
1&!
b1110100101 #!
#815
0!
0O
0W
0]
0c
0i
0s
0x
0&!
#820
1!
1O
1W
1]
1c
1i
1s
1x
1&!
b1110100011 #!
#825
0!
0O
0W
0]
0c
0i
0s
0x
0&!
#830
1!
1O
1W
1]
1c
1i
1s
1x
1&!
b1110100001 #!
#835
0!
0O
0W
0]
0c
0i
0s
0x
0&!
#840
1!
1O
1W
1]
1c
1i
1s
1x
1&!
b1110011111 #!
#845
0!
0O
0W
0]
0c
0i
0s
0x
0&!
#850
1!
1O
1W
1]
1c
1i
1s
1x
1&!
b1110011101 #!
#855
0!
0O
0W
0]
0c
0i
0s
0x
0&!
#860
1!
1O
1W
1]
1c
1i
1s
1x
1&!
b1110011011 #!
#865
0!
0O
0W
0]
0c
0i
0s
0x
0&!
#870
1!
1O
1W
1]
1c
1i
1s
1x
1&!
b1110011001 #!
#875
0!
0O
0W
0]
0c
0i
0s
0x
0&!
#880
1!
1O
1W
1]
1c
1i
1s
1x
1&!
b1110010111 #!
#885
0!
0O
0W
0]
0c
0i
0s
0x
0&!
#890
1!
1O
1W
1]
1c
1i
1s
1x
1&!
b1110010101 #!
#895
0!
0O
0W
0]
0c
0i
0s
0x
0&!
#900
1!
1O
1W
1]
1c
1i
1s
1x
1&!
b1110010011 #!
#905
0!
0O
0W
0]
0c
0i
0s
0x
0&!
#910
1!
1O
1W
1]
1c
1i
1s
1x
1&!
b1110010001 #!
#915
0!
0O
0W
0]
0c
0i
0s
0x
0&!
#920
1!
1O
1W
1]
1c
1i
1s
1x
1&!
b1110001111 #!
#925
0!
0O
0W
0]
0c
0i
0s
0x
0&!
#930
1!
1O
1W
1]
1c
1i
1s
1x
1&!
b1110001101 #!
#935
0!
0O
0W
0]
0c
0i
0s
0x
0&!
#940
1!
1O
1W
1]
1c
1i
1s
1x
1&!
b1110001011 #!
#945
0!
0O
0W
0]
0c
0i
0s
0x
0&!
#950
1!
1O
1W
1]
1c
1i
1s
1x
1&!
b1110001001 #!
#955
0!
0O
0W
0]
0c
0i
0s
0x
0&!
#960
1!
1O
1W
1]
1c
1i
1s
1x
1&!
b1110000111 #!
#965
0!
0O
0W
0]
0c
0i
0s
0x
0&!
#970
1!
1O
1W
1]
1c
1i
1s
1x
1&!
b1110000101 #!
#975
0!
0O
0W
0]
0c
0i
0s
0x
0&!
#980
1!
1O
1W
1]
1c
1i
1s
1x
1&!
b1110000011 #!
#985
0!
0O
0W
0]
0c
0i
0s
0x
0&!
#990
1!
1O
1W
1]
1c
1i
1s
1x
1&!
b1110000001 #!
#995
0!
0O
0W
0]
0c
0i
0s
0x
0&!
#1000
1!
1O
1W
1]
1c
1i
1s
1x
1&!
b1101111111 #!
#1005
0!
0O
0W
0]
0c
0i
0s
0x
0&!
#1010
1!
1O
1W
1]
1c
1i
1s
1x
1&!
b1101111101 #!
#1015
0!
0O
0W
0]
0c
0i
0s
0x
0&!
#1020
1!
1O
1W
1]
1c
1i
1s
1x
1&!
b1101111011 #!
#1025
0!
0O
0W
0]
0c
0i
0s
0x
0&!
#1030
1!
1O
1W
1]
1c
1i
1s
1x
1&!
b1101111001 #!
#1035
0!
0O
0W
0]
0c
0i
0s
0x
0&!
#1040
1!
1O
1W
1]
1c
1i
1s
1x
1&!
b1101110111 #!
#1045
0!
0O
0W
0]
0c
0i
0s
0x
0&!
#1050
1!
1O
1W
1]
1c
1i
1s
1x
1&!
b1101110101 #!
#1055
0!
0O
0W
0]
0c
0i
0s
0x
0&!
#1060
1!
1O
1W
1]
1c
1i
1s
1x
1&!
b1101110011 #!
#1065
0!
0O
0W
0]
0c
0i
0s
0x
0&!
#1070
1!
1O
1W
1]
1c
1i
1s
1x
1&!
b1101110001 #!
#1075
0!
0O
0W
0]
0c
0i
0s
0x
0&!
#1080
1!
1O
1W
1]
1c
1i
1s
1x
1&!
b1101101111 #!
#1085
0!
0O
0W
0]
0c
0i
0s
0x
0&!
#1090
1!
1O
1W
1]
1c
1i
1s
1x
1&!
b1101101101 #!
#1095
0!
0O
0W
0]
0c
0i
0s
0x
0&!
#1100
1!
1O
1W
1]
1c
1i
1s
1x
1&!
b1101101011 #!
#1105
0!
0O
0W
0]
0c
0i
0s
0x
0&!
#1110
1!
1O
1W
1]
1c
1i
1s
1x
1&!
b1101101001 #!
#1115
0!
0O
0W
0]
0c
0i
0s
0x
0&!
#1120
1!
1O
1W
1]
1c
1i
1s
1x
1&!
b1101100111 #!
#1125
0!
0O
0W
0]
0c
0i
0s
0x
0&!
#1130
1!
1O
1W
1]
1c
1i
1s
1x
1&!
b1101100101 #!
#1135
0!
0O
0W
0]
0c
0i
0s
0x
0&!
#1140
1!
1O
1W
1]
1c
1i
1s
1x
1&!
b1101100011 #!
#1145
0!
0O
0W
0]
0c
0i
0s
0x
0&!
#1150
1!
1O
1W
1]
1c
1i
1s
1x
1&!
b1101100001 #!
#1155
0!
0O
0W
0]
0c
0i
0s
0x
0&!
#1160
1!
1O
1W
1]
1c
1i
1s
1x
1&!
b1101011111 #!
#1165
0!
0O
0W
0]
0c
0i
0s
0x
0&!
#1170
1!
1O
1W
1]
1c
1i
1s
1x
1&!
b1101011101 #!
#1175
0!
0O
0W
0]
0c
0i
0s
0x
0&!
#1180
1!
1O
1W
1]
1c
1i
1s
1x
1&!
b1101011011 #!
#1185
0!
0O
0W
0]
0c
0i
0s
0x
0&!
#1190
1!
1O
1W
1]
1c
1i
1s
1x
1&!
b1101011001 #!
#1195
0!
0O
0W
0]
0c
0i
0s
0x
0&!
#1200
1!
1O
1W
1]
1c
1i
1s
1x
1&!
b1101010111 #!
#1205
0!
0O
0W
0]
0c
0i
0s
0x
0&!
#1210
1!
1O
1W
1]
1c
1i
1s
1x
1&!
b1101010101 #!
